<?xml version="1.0"?>
<!DOCTYPE assetlist>

<assetlist author="Areldir" name="Mercury_Temple">
<!-- Note: Mercury Complex Construction 01-05 are the 0%, 25%, 50%, 75% and 100% construction phases respectively -->
    <image id="Mercury Complex Const 01" src="Mercury_Temple_Complex_Construction_01" />
    <image id="Mercury Complex Const 02" src="Mercury_Temple_Complex_Construction_02" />	
    <image id="Mercury Complex Const 03" src="Mercury_Temple_Complex_Construction_03" />	
    <image id="Mercury Complex Const 04" src="Mercury_Temple_Complex_Construction_04" />	
    <image id="Mercury Complex Const 05" width="418" height="231">
	    <layer src="Mercury_Temple_Complex_Construction_03" />
		<layer group="73" image="1" x="150" y="8" />
	</image>
<!-- Note: Mercury Complex ON/OFF States -->
    <image id="Mercury Complex Off" width="418" height="231">
        <layer src="Mercury_Temple_Complex_Base_Layer" />
		<layer group="73" image="1" x="150" y="8" />
        <layer src="Mercury_Temple_Complex_Top_Layer" x="199" y="79" />
    </image>
    <image id="Mercury Complex On" width="418" height="231">
		<layer group="this" image="Mercury Complex Off" />
        <layer src="Mercury_Temple_Complex_On_Layer" x="135" y="117" />
    </image>		
<!-- Note: Mercury Complex Module Animation (Priests reduce Oil/Wine consumption) -->
    <image id="Mercury Complex Module" width="418" height="231">
		<layer group="this" image="Mercury Complex Off" />
        <animation speed="5" frames="3" x="115" y="105" reversible="true" />
    </image>
    <image src="Mercury_Temple_Complex_Module_01" />
    <image src="Mercury_Temple_Complex_Module_02" />
    <image src="Mercury_Temple_Complex_Module_03" />
<!-- Note: Mercury Complex Module2 Animation (Priests reduce Pottery/Furniture consumption) -->
    <image id="Mercury Complex Module2" width="418" height="231">
		<layer group="this" image="Mercury Complex Off" />
        <animation speed="5" frames="3" x="94" y="103" reversible="true" />
    </image>
    <image src="Mercury_Temple_Complex_Module2_01" />
    <image src="Mercury_Temple_Complex_Module2_02" />
    <image src="Mercury_Temple_Complex_Module2_03" />

</assetlist>	